TestRailAPIClient.py
TestRailListener.py
TestRailPreRunModifier.py
robotframework_testrail_correct_link-1.1.dist-info/METADATA
robotframework_testrail_correct_link-1.1.dist-info/WHEEL
robotframework_testrail_correct_link-1.1.dist-info/top_level.txt
robotframework_testrail_correct_link-1.1.dist-info/RECORD
