Metadata-Version: 2.1
Name: robotframework-testrail-correct-link
Version: 1.1
Summary: Robot Framework library, listener and pre-run modifier for working with TestRail
Home-page: https://github.com/MrVeshij/robotframework-testrail-correct-link
Author: veshij
Author-email: veshij@bk.ru
License: UNKNOWN
Keywords: testing testautomation robotframework testrail correct link
Platform: UNKNOWN
Classifier: Development Status :: 5 - Production/Stable
Classifier: Intended Audience :: Developers
Classifier: Topic :: Software Development :: Testing
Classifier: License :: OSI Approved :: Apache Software License
Classifier: Programming Language :: Python :: 3.5
Classifier: Programming Language :: Python :: 3.6
Classifier: Framework :: Robot Framework :: Library
Requires-Dist: requests (>=2.20.0)
Requires-Dist: robotframework (>=3.0.3)
Requires-Dist: future (==0.16.0) ; python_version <= "2.7"
